batched_queue/result.py
batched_queue/py.typed
batched_queue/queue.py
batched_queue/incrementer.cpython-311-aarch64-linux-gnu.so
batched_queue/__init__.py
batched_queue/incrementer.pyx
batched_queue/incrementer.pyi
batched_queue/incrementer.c
batched_queue/types.py
batched_queue-0.1.3.dist-info/RECORD
batched_queue-0.1.3.dist-info/WHEEL
batched_queue-0.1.3.dist-info/LICENSE
batched_queue-0.1.3.dist-info/METADATA
